[{
  "_id": {
    "$oid": "666cabc090edab7d6c458d23"
  },
  "ResponseId": "db6e8b5e-5a65-4efd-9e6c-5baafbaea179-f5fea8aa",
  "Name": "Ilyas",
  "Email": "mohammadilyassilat0@gmail.com",
  "PhoneNumber": {
    "$numberLong": "3212921053"
  },
  "createdAt": {
    "$date": "2024-06-14T20:44:48.346Z"
  },
  "updatedAt": {
    "$date": "2024-06-14T20:44:48.348Z"
  },
  "__v": 0
},
{
  "_id": {
    "$oid": "666cacfb37d58af1f3b41b78"
  },
  "ResponseId": "d2e39b22-70c2-40f0-afc7-f63fb924c4ac-f5fea8aa",
  "Name": "Ilyas",
  "Email": "1375219.aptechiic@gmail.com",
  "PhoneNumber": {
    "$numberLong": "3212921053"
  },
  "createdAt": {
    "$date": "2024-06-14T20:50:03.162Z"
  },
  "updatedAt": {
    "$date": "2024-06-14T20:50:03.162Z"
  },
  "__v": 0
},
{
  "_id": {
    "$oid": "666f0ed16a2a7e5e5e884517"
  },
  "ResponseId": "2c4b5bc9-f52b-404f-afc9-bc1f3e8f0e2b-f5fea8aa",
  "Name": "Ilyas",
  "Email": "mohammadilyassilat0@gmail.com",
  "PhoneNumber": {
    "$numberLong": "3212921053"
  },
  "createdAt": {
    "$date": "2024-06-16T16:12:01.799Z"
  },
  "__v": 0
},
{
  "_id": {
    "$oid": "666f0f36e2e29c7b4d40bd37"
  },
  "ResponseId": "ca99ddae-fe2c-4df7-ada0-442f484ab407-f5fea8aa",
  "Name": "Ilyas",
  "Email": "1375219.aptechiic@gmail.com",
  "PhoneNumber": {
    "$numberLong": "3212921053"
  },
  "createdAt": {
    "$date": "2024-06-16T16:13:42.406Z"
  },
  "__v": 0
}]